brainball_cpp_engine.cp310-win_amd64.pyd
gfootball/__init__.py
gfootball/build_game_engine.bat
gfootball/build_game_engine.sh
gfootball/dump_to_txt.py
gfootball/dump_to_video.py
gfootball/play_game.py
gfootball/replay.py
gfootball/colabs/gfootball_example_from_prebuild.ipynb
gfootball/colabs/gfootball_example_from_scratch.ipynb
gfootball/doc/api.md
gfootball/doc/compile_engine.md
gfootball/doc/docker.md
gfootball/doc/imitation.md
gfootball/doc/multi_agent.md
gfootball/doc/observation.md
gfootball/doc/saving_replays.md
gfootball/doc/scenarios.md
gfootball/env/__init__.py
gfootball/env/config.py
gfootball/env/constants.py
gfootball/env/controller_base.py
gfootball/env/event_queue.py
gfootball/env/football_action_set.py
gfootball/env/football_action_set_test.py
gfootball/env/football_env.py
gfootball/env/football_env_core.py
gfootball/env/football_env_test.py
gfootball/env/gym_test.py
gfootball/env/observation_preprocessing.py
gfootball/env/observation_processor.py
gfootball/env/observation_rotation.py
gfootball/env/observation_rotation_test.py
gfootball/env/player_base.py
gfootball/env/remote_football_env.py
gfootball/env/scenario_builder.py
gfootball/env/script_helpers.py
gfootball/env/script_helpers_test.py
gfootball/env/wrappers.py
gfootball/env/wrappers_test.py
gfootball/env/players/__init__.py
gfootball/env/players/agent.py
gfootball/env/players/bot.py
gfootball/env/players/gamepad.py
gfootball/env/players/keyboard.py
gfootball/env/players/lazy.py
gfootball/env/players/ppo2_cnn.py
gfootball/env/players/replay.py
gfootball/eval_server/__init__.py
gfootball/eval_server/config.py
gfootball/eval_server/example_client.py
gfootball/eval_server/utils.py
gfootball/eval_server/proto/game_server.proto
gfootball/eval_server/proto/game_server_pb2.py
gfootball/eval_server/proto/game_server_pb2_grpc.py
gfootball/eval_server/proto/master.proto
gfootball/eval_server/proto/master_pb2.py
gfootball/eval_server/proto/master_pb2_grpc.py
gfootball/examples/__init__.py
gfootball-2.10.2.dist-info/LICENSE
gfootball-2.10.2.dist-info/METADATA
gfootball-2.10.2.dist-info/WHEEL
gfootball-2.10.2.dist-info/top_level.txt
gfootball-2.10.2.dist-info/RECORD
