Metadata-Version: 2.1
Name: gfootball
Version: 2.10.2
Summary: Google Research Football - RL environment based on open-source game Gameplay Football
Home-page: https://github.com/google-research/football
Author: Google LLC
Author-email: no-reply@google.com
License: Apache 2.0
Keywords: gfootball reinforcement-learning python machine learning
Platform: UNKNOWN
License-File: LICENSE
Requires-Dist: pygame (>=1.9.6)
Requires-Dist: opencv-python
Requires-Dist: psutil
Requires-Dist: scipy
Requires-Dist: gym (>=0.11.0)
Requires-Dist: absl-py
Requires-Dist: wheel
